{
  "SaveName": "",
  "Date": "",
  "VersionNumber": "",
  "GameMode": "",
  "GameType": "",
  "GameComplexity": "",
  "Tags": [],
  "Gravity": 0.5,
  "PlayArea": 0.5,
  "Table": "",
  "Sky": "",
  "Note": "",
  "TabStates": {},
  "LuaScript": "",
  "LuaScriptState": "",
  "XmlUI": "",
  "ObjectStates": [
    {
      "GUID": "20d762",
      "Name": "Deck",
      "Transform": {
        "posX": 17.8234463,
        "posY": 1.13498008,
        "posZ": 12.1804352,
        "rotX": -6.73011868E-07,
        "rotY": 180.0,
        "rotZ": -1.63733617E-07,
        "scaleX": 1.25,
        "scaleY": 1.0,
        "scaleZ": 1.25
      },
      "Nickname": "Emperor",
      "Description": "By PolterGhost\nArchetype: Control\nR2/Z3/C3",
      "GMNotes": "",
      "ColorDiffuse": {
        "r": 0.713235259,
        "g": 0.713235259,
        "b": 0.713235259
      },
      "LayoutGroupSortIndex": 0,
      "Value": 0,
      "Locked": false,
      "Grid": true,
      "Snap": true,
      "IgnoreFoW": false,
      "MeasureMovement": false,
      "DragSelectable": true,
      "Autoraise": true,
      "Sticky": true,
      "Tooltip": true,
      "GridProjection": false,
      "HideWhenFaceDown": true,
      "Hands": false,
      "SidewaysCard": false,
      "DeckIDs": [
        831807,
        831807,
        831806,
        831806,
        831805,
        831805,
        831804,
        831804,
        831803,
        831803,
        831802,
        831802,
        831801,
        831801,
        831800,
        831800,
        575106,
        575106,
        575105,
        575105,
        575104,
        575104,
        575103,
        575103,
        575102,
        575102,
        575101,
        575101,
        575100,
        575100,
        574500,
        575400
      ],
      "CustomDeck": {
        "8318": {
          "FaceURL": "https://i.imgur.com/pJw6uZi.png",
          "BackURL": "https://i.imgur.com/Yq7iMBt.jpg",
          "NumWidth": 3,
          "NumHeight": 3,
          "BackIsHidden": true,
          "UniqueBack": false,
          "Type": 0
        },
        "5751": {
          "FaceURL": "https://i.imgur.com/5eX2P1b.jpg",
          "BackURL": "https://i.imgur.com/xSQrDAv.jpg",
          "NumWidth": 4,
          "NumHeight": 2,
          "BackIsHidden": true,
          "UniqueBack": false,
          "Type": 0
        },
        "5745": {
          "FaceURL": "https://i.imgur.com/GGjkL5w.png",
          "BackURL": "https://i.imgur.com/63DdgrF.png",
          "NumWidth": 1,
          "NumHeight": 1,
          "BackIsHidden": true,
          "UniqueBack": false,
          "Type": 0
        },
        "5754": {
          "FaceURL": "https://i.imgur.com/7pUeMzo.png",
          "BackURL": "https://i.imgur.com/LKePOkb.png",
          "NumWidth": 1,
          "NumHeight": 1,
          "BackIsHidden": true,
          "UniqueBack": false,
          "Type": 0
        }
      },
      "LuaScript": "",
      "LuaScriptState": "",
      "XmlUI": "",
      "ContainedObjects": [
        {
          "GUID": "51e83c",
          "Name": "Card",
          "Transform": {
            "posX": 2.75921369,
            "posY": 0.973562956,
            "posZ": 23.107233,
            "rotX": 0.000345487468,
            "rotY": 5.849426E-06,
            "rotZ": -0.00218528463,
            "scaleX": 1.25,
            "scaleY": 1.0,
            "scaleZ": 1.25
          },
          "Nickname": "Block (N)",
          "Description": "",
          "GMNotes": "",
          "ColorDiffuse": {
            "r": 0.713235259,
            "g": 0.713235259,
            "b": 0.713235259
          },
          "LayoutGroupSortIndex": 0,
          "Value": 0,
          "Locked": false,
          "Grid": true,
          "Snap": true,
          "IgnoreFoW": false,
          "MeasureMovement": false,
          "DragSelectable": true,
          "Autoraise": true,
          "Sticky": true,
          "Tooltip": true,
          "GridProjection": false,
          "HideWhenFaceDown": true,
          "Hands": true,
          "CardID": 831807,
          "SidewaysCard": false,
          "CustomDeck": {
            "8318": {
              "FaceURL": "https://i.imgur.com/pJw6uZi.png",
              "BackURL": "https://i.imgur.com/Yq7iMBt.jpg",
              "NumWidth": 3,
              "NumHeight": 3,
              "BackIsHidden": true,
              "UniqueBack": false,
              "Type": 0
            }
          },
          "LuaScript": "",
          "LuaScriptState": "",
          "XmlUI": ""
        },
        {
          "GUID": "72adbd",
          "Name": "Card",
          "Transform": {
            "posX": 2.795882,
            "posY": 1.0094099,
            "posZ": 23.11363,
            "rotX": 0.0118222926,
            "rotY": 1.38788073E-06,
            "rotZ": 359.984772,
            "scaleX": 1.25,
            "scaleY": 1.0,
            "scaleZ": 1.25
          },
          "Nickname": "Block (N)",
          "Description": "",
          "GMNotes": "",
          "ColorDiffuse": {
            "r": 0.713235259,
            "g": 0.713235259,
            "b": 0.713235259
          },
          "LayoutGroupSortIndex": 0,
          "Value": 0,
          "Locked": false,
          "Grid": true,
          "Snap": true,
          "IgnoreFoW": false,
          "MeasureMovement": false,
          "DragSelectable": true,
          "Autoraise": true,
          "Sticky": true,
          "Tooltip": true,
          "GridProjection": false,
          "HideWhenFaceDown": true,
          "Hands": true,
          "CardID": 831807,
          "SidewaysCard": false,
          "CustomDeck": {
            "8318": {
              "FaceURL": "https://i.imgur.com/pJw6uZi.png",
              "BackURL": "https://i.imgur.com/Yq7iMBt.jpg",
              "NumWidth": 3,
              "NumHeight": 3,
              "BackIsHidden": true,
              "UniqueBack": false,
              "Type": 0
            }
          },
          "LuaScript": "",
          "LuaScriptState": "",
          "XmlUI": ""
        },
        {
          "GUID": "69ffff",
          "Name": "Card",
          "Transform": {
            "posX": 2.905885,
            "posY": 1.06156409,
            "posZ": 23.53015,
            "rotX": 0.00793772,
            "rotY": -0.00382506684,
            "rotZ": 359.494354,
            "scaleX": 1.25,
            "scaleY": 1.0,
            "scaleZ": 1.25
          },
          "Nickname": "Focus (N)",
          "Description": "",
          "GMNotes": "",
          "ColorDiffuse": {
            "r": 0.713235259,
            "g": 0.713235259,
            "b": 0.713235259
          },
          "LayoutGroupSortIndex": 0,
          "Value": 0,
          "Locked": false,
          "Grid": true,
          "Snap": true,
          "IgnoreFoW": false,
          "MeasureMovement": false,
          "DragSelectable": true,
          "Autoraise": true,
          "Sticky": true,
          "Tooltip": true,
          "GridProjection": false,
          "HideWhenFaceDown": true,
          "Hands": true,
          "CardID": 831806,
          "SidewaysCard": false,
          "CustomDeck": {
            "8318": {
              "FaceURL": "https://i.imgur.com/pJw6uZi.png",
              "BackURL": "https://i.imgur.com/Yq7iMBt.jpg",
              "NumWidth": 3,
              "NumHeight": 3,
              "BackIsHidden": true,
              "UniqueBack": false,
              "Type": 0
            }
          },
          "LuaScript": "",
          "LuaScriptState": "",
          "XmlUI": ""
        },
        {
          "GUID": "98c2bb",
          "Name": "Card",
          "Transform": {
            "posX": 2.43437934,
            "posY": 1.05883825,
            "posZ": 22.9620838,
            "rotX": 0.0004647228,
            "rotY": -0.0011795772,
            "rotZ": -0.0005139419,
            "scaleX": 1.25,
            "scaleY": 1.0,
            "scaleZ": 1.25
          },
          "Nickname": "Focus (N)",
          "Description": "",
          "GMNotes": "",
          "ColorDiffuse": {
            "r": 0.713235259,
            "g": 0.713235259,
            "b": 0.713235259
          },
          "LayoutGroupSortIndex": 0,
          "Value": 0,
          "Locked": false,
          "Grid": true,
          "Snap": true,
          "IgnoreFoW": false,
          "MeasureMovement": false,
          "DragSelectable": true,
          "Autoraise": true,
          "Sticky": true,
          "Tooltip": true,
          "GridProjection": false,
          "HideWhenFaceDown": true,
          "Hands": true,
          "CardID": 831806,
          "SidewaysCard": false,
          "CustomDeck": {
            "8318": {
              "FaceURL": "https://i.imgur.com/pJw6uZi.png",
              "BackURL": "https://i.imgur.com/Yq7iMBt.jpg",
              "NumWidth": 3,
              "NumHeight": 3,
              "BackIsHidden": true,
              "UniqueBack": false,
              "Type": 0
            }
          },
          "LuaScript": "",
          "LuaScriptState": "",
          "XmlUI": ""
        },
        {
          "GUID": "a33ff7",
          "Name": "Card",
          "Transform": {
            "posX": 2.48415136,
            "posY": 1.0994786,
            "posZ": 23.1894264,
            "rotX": -0.00132408517,
            "rotY": 0.0133599024,
            "rotZ": 1.37554955,
            "scaleX": 1.25,
            "scaleY": 1.0,
            "scaleZ": 1.25
          },
          "Nickname": "Sweep (N)",
          "Description": "",
          "GMNotes": "",
          "ColorDiffuse": {
            "r": 0.713235259,
            "g": 0.713235259,
            "b": 0.713235259
          },
          "LayoutGroupSortIndex": 0,
          "Value": 0,
          "Locked": false,
          "Grid": true,
          "Snap": true,
          "IgnoreFoW": false,
          "MeasureMovement": false,
          "DragSelectable": true,
          "Autoraise": true,
          "Sticky": true,
          "Tooltip": true,
          "GridProjection": false,
          "HideWhenFaceDown": true,
          "Hands": true,
          "CardID": 831805,
          "SidewaysCard": false,
          "CustomDeck": {
            "8318": {
              "FaceURL": "https://i.imgur.com/pJw6uZi.png",
              "BackURL": "https://i.imgur.com/Yq7iMBt.jpg",
              "NumWidth": 3,
              "NumHeight": 3,
              "BackIsHidden": true,
              "UniqueBack": false,
              "Type": 0
            }
          },
          "LuaScript": "",
          "LuaScriptState": "",
          "XmlUI": ""
        },
        {
          "GUID": "2891ec",
          "Name": "Card",
          "Transform": {
            "posX": 3.20930815,
            "posY": 1.13003063,
            "posZ": 22.4264526,
            "rotX": 359.562347,
            "rotY": 359.982422,
            "rotZ": 1.67238224,
            "scaleX": 1.25,
            "scaleY": 1.0,
            "scaleZ": 1.25
          },
          "Nickname": "Sweep (N)",
          "Description": "",
          "GMNotes": "",
          "ColorDiffuse": {
            "r": 0.713235259,
            "g": 0.713235259,
            "b": 0.713235259
          },
          "LayoutGroupSortIndex": 0,
          "Value": 0,
          "Locked": false,
          "Grid": true,
          "Snap": true,
          "IgnoreFoW": false,
          "MeasureMovement": false,
          "DragSelectable": true,
          "Autoraise": true,
          "Sticky": true,
          "Tooltip": true,
          "GridProjection": false,
          "HideWhenFaceDown": true,
          "Hands": true,
          "CardID": 831805,
          "SidewaysCard": false,
          "CustomDeck": {
            "8318": {
              "FaceURL": "https://i.imgur.com/pJw6uZi.png",
              "BackURL": "https://i.imgur.com/Yq7iMBt.jpg",
              "NumWidth": 3,
              "NumHeight": 3,
              "BackIsHidden": true,
              "UniqueBack": false,
              "Type": 0
            }
          },
          "LuaScript": "",
          "LuaScriptState": "",
          "XmlUI": ""
        },
        {
          "GUID": "b3352c",
          "Name": "Card",
          "Transform": {
            "posX": 2.66152167,
            "posY": 1.09801435,
            "posZ": 22.7255669,
            "rotX": 359.675629,
            "rotY": 0.00128614018,
            "rotZ": 0.0500568859,
            "scaleX": 1.25,
            "scaleY": 1.0,
            "scaleZ": 1.25
          },
          "Nickname": "Spike (N)",
          "Description": "",
          "GMNotes": "",
          "ColorDiffuse": {
            "r": 0.713235259,
            "g": 0.713235259,
            "b": 0.713235259
          },
          "LayoutGroupSortIndex": 0,
          "Value": 0,
          "Locked": false,
          "Grid": true,
          "Snap": true,
          "IgnoreFoW": false,
          "MeasureMovement": false,
          "DragSelectable": true,
          "Autoraise": true,
          "Sticky": true,
          "Tooltip": true,
          "GridProjection": false,
          "HideWhenFaceDown": true,
          "Hands": true,
          "CardID": 831804,
          "SidewaysCard": false,
          "CustomDeck": {
            "8318": {
              "FaceURL": "https://i.imgur.com/pJw6uZi.png",
              "BackURL": "https://i.imgur.com/Yq7iMBt.jpg",
              "NumWidth": 3,
              "NumHeight": 3,
              "BackIsHidden": true,
              "UniqueBack": false,
              "Type": 0
            }
          },
          "LuaScript": "",
          "LuaScriptState": "",
          "XmlUI": ""
        },
        {
          "GUID": "666cbc",
          "Name": "Card",
          "Transform": {
            "posX": 2.62458062,
            "posY": 1.10047066,
            "posZ": 22.67259,
            "rotX": 0.09314921,
            "rotY": 0.003327763,
            "rotZ": 0.008302319,
            "scaleX": 1.25,
            "scaleY": 1.0,
            "scaleZ": 1.25
          },
          "Nickname": "Spike (N)",
          "Description": "",
          "GMNotes": "",
          "ColorDiffuse": {
            "r": 0.713235259,
            "g": 0.713235259,
            "b": 0.713235259
          },
          "LayoutGroupSortIndex": 0,
          "Value": 0,
          "Locked": false,
          "Grid": true,
          "Snap": true,
          "IgnoreFoW": false,
          "MeasureMovement": false,
          "DragSelectable": true,
          "Autoraise": true,
          "Sticky": true,
          "Tooltip": true,
          "GridProjection": false,
          "HideWhenFaceDown": true,
          "Hands": true,
          "CardID": 831804,
          "SidewaysCard": false,
          "CustomDeck": {
            "8318": {
              "FaceURL": "https://i.imgur.com/pJw6uZi.png",
              "BackURL": "https://i.imgur.com/Yq7iMBt.jpg",
              "NumWidth": 3,
              "NumHeight": 3,
              "BackIsHidden": true,
              "UniqueBack": false,
              "Type": 0
            }
          },
          "LuaScript": "",
          "LuaScriptState": "",
          "XmlUI": ""
        },
        {
          "GUID": "3b8f45",
          "Name": "Card",
          "Transform": {
            "posX": 3.861324,
            "posY": 1.09984207,
            "posZ": 23.2119026,
            "rotX": 0.00213425746,
            "rotY": -1.778859E-05,
            "rotZ": 359.986633,
            "scaleX": 1.25,
            "scaleY": 1.0,
            "scaleZ": 1.25
          },
          "Nickname": "Dive (N)",
          "Description": "",
          "GMNotes": "",
          "ColorDiffuse": {
            "r": 0.713235259,
            "g": 0.713235259,
            "b": 0.713235259
          },
          "LayoutGroupSortIndex": 0,
          "Value": 0,
          "Locked": false,
          "Grid": true,
          "Snap": true,
          "IgnoreFoW": false,
          "MeasureMovement": false,
          "DragSelectable": true,
          "Autoraise": true,
          "Sticky": true,
          "Tooltip": true,
          "GridProjection": false,
          "HideWhenFaceDown": true,
          "Hands": true,
          "CardID": 831803,
          "SidewaysCard": false,
          "CustomDeck": {
            "8318": {
              "FaceURL": "https://i.imgur.com/pJw6uZi.png",
              "BackURL": "https://i.imgur.com/Yq7iMBt.jpg",
              "NumWidth": 3,
              "NumHeight": 3,
              "BackIsHidden": true,
              "UniqueBack": false,
              "Type": 0
            }
          },
          "LuaScript": "",
          "LuaScriptState": "",
          "XmlUI": ""
        },
        {
          "GUID": "11f76f",
          "Name": "Card",
          "Transform": {
            "posX": 2.95109653,
            "posY": 1.11664414,
            "posZ": 23.1059589,
            "rotX": -0.000140789663,
            "rotY": -3.424606E-07,
            "rotZ": -0.0004590317,
            "scaleX": 1.25,
            "scaleY": 1.0,
            "scaleZ": 1.25
          },
          "Nickname": "Dive (N)",
          "Description": "",
          "GMNotes": "",
          "ColorDiffuse": {
            "r": 0.713235259,
            "g": 0.713235259,
            "b": 0.713235259
          },
          "LayoutGroupSortIndex": 0,
          "Value": 0,
          "Locked": false,
          "Grid": true,
          "Snap": true,
          "IgnoreFoW": false,
          "MeasureMovement": false,
          "DragSelectable": true,
          "Autoraise": true,
          "Sticky": true,
          "Tooltip": true,
          "GridProjection": false,
          "HideWhenFaceDown": true,
          "Hands": true,
          "CardID": 831803,
          "SidewaysCard": false,
          "CustomDeck": {
            "8318": {
              "FaceURL": "https://i.imgur.com/pJw6uZi.png",
              "BackURL": "https://i.imgur.com/Yq7iMBt.jpg",
              "NumWidth": 3,
              "NumHeight": 3,
              "BackIsHidden": true,
              "UniqueBack": false,
              "Type": 0
            }
          },
          "LuaScript": "",
          "LuaScriptState": "",
          "XmlUI": ""
        },
        {
          "GUID": "b75f92",
          "Name": "Card",
          "Transform": {
            "posX": 3.03975677,
            "posY": 1.11549854,
            "posZ": 22.99117,
            "rotX": 0.0009802809,
            "rotY": 359.994019,
            "rotZ": -0.00113500992,
            "scaleX": 1.25,
            "scaleY": 1.0,
            "scaleZ": 1.25
          },
          "Nickname": "Assault (N)",
          "Description": "",
          "GMNotes": "",
          "ColorDiffuse": {
            "r": 0.713235259,
            "g": 0.713235259,
            "b": 0.713235259
          },
          "LayoutGroupSortIndex": 0,
          "Value": 0,
          "Locked": false,
          "Grid": true,
          "Snap": true,
          "IgnoreFoW": false,
          "MeasureMovement": false,
          "DragSelectable": true,
          "Autoraise": true,
          "Sticky": true,
          "Tooltip": true,
          "GridProjection": false,
          "HideWhenFaceDown": true,
          "Hands": true,
          "CardID": 831802,
          "SidewaysCard": false,
          "CustomDeck": {
            "8318": {
              "FaceURL": "https://i.imgur.com/pJw6uZi.png",
              "BackURL": "https://i.imgur.com/Yq7iMBt.jpg",
              "NumWidth": 3,
              "NumHeight": 3,
              "BackIsHidden": true,
              "UniqueBack": false,
              "Type": 0
            }
          },
          "LuaScript": "",
          "LuaScriptState": "",
          "XmlUI": ""
        },
        {
          "GUID": "d5e589",
          "Name": "Card",
          "Transform": {
            "posX": 3.072246,
            "posY": 1.135874,
            "posZ": 22.8739529,
            "rotX": 0.0002878789,
            "rotY": 359.994019,
            "rotZ": -0.000385395979,
            "scaleX": 1.25,
            "scaleY": 1.0,
            "scaleZ": 1.25
          },
          "Nickname": "Assault (N)",
          "Description": "",
          "GMNotes": "",
          "ColorDiffuse": {
            "r": 0.713235259,
            "g": 0.713235259,
            "b": 0.713235259
          },
          "LayoutGroupSortIndex": 0,
          "Value": 0,
          "Locked": false,
          "Grid": true,
          "Snap": true,
          "IgnoreFoW": false,
          "MeasureMovement": false,
          "DragSelectable": true,
          "Autoraise": true,
          "Sticky": true,
          "Tooltip": true,
          "GridProjection": false,
          "HideWhenFaceDown": true,
          "Hands": true,
          "CardID": 831802,
          "SidewaysCard": false,
          "CustomDeck": {
            "8318": {
              "FaceURL": "https://i.imgur.com/pJw6uZi.png",
              "BackURL": "https://i.imgur.com/Yq7iMBt.jpg",
              "NumWidth": 3,
              "NumHeight": 3,
              "BackIsHidden": true,
              "UniqueBack": false,
              "Type": 0
            }
          },
          "LuaScript": "",
          "LuaScriptState": "",
          "XmlUI": ""
        },
        {
          "GUID": "e1b2ec",
          "Name": "Card",
          "Transform": {
            "posX": 2.95073366,
            "posY": 1.14494324,
            "posZ": 23.1013489,
            "rotX": 0.000375872245,
            "rotY": 359.991241,
            "rotZ": -0.000325480331,
            "scaleX": 1.25,
            "scaleY": 1.0,
            "scaleZ": 1.25
          },
          "Nickname": "Cross (N)",
          "Description": "",
          "GMNotes": "",
          "ColorDiffuse": {
            "r": 0.713235259,
            "g": 0.713235259,
            "b": 0.713235259
          },
          "LayoutGroupSortIndex": 0,
          "Value": 0,
          "Locked": false,
          "Grid": true,
          "Snap": true,
          "IgnoreFoW": false,
          "MeasureMovement": false,
          "DragSelectable": true,
          "Autoraise": true,
          "Sticky": true,
          "Tooltip": true,
          "GridProjection": false,
          "HideWhenFaceDown": true,
          "Hands": true,
          "CardID": 831801,
          "SidewaysCard": false,
          "CustomDeck": {
            "8318": {
              "FaceURL": "https://i.imgur.com/pJw6uZi.png",
              "BackURL": "https://i.imgur.com/Yq7iMBt.jpg",
              "NumWidth": 3,
              "NumHeight": 3,
              "BackIsHidden": true,
              "UniqueBack": false,
              "Type": 0
            }
          },
          "LuaScript": "",
          "LuaScriptState": "",
          "XmlUI": ""
        },
        {
          "GUID": "9532fa",
          "Name": "Card",
          "Transform": {
            "posX": 3.11762762,
            "posY": 1.15512717,
            "posZ": 23.0071259,
            "rotX": 0.000316116144,
            "rotY": 359.991241,
            "rotZ": -0.000470857369,
            "scaleX": 1.25,
            "scaleY": 1.0,
            "scaleZ": 1.25
          },
          "Nickname": "Cross (N)",
          "Description": "",
          "GMNotes": "",
          "ColorDiffuse": {
            "r": 0.713235259,
            "g": 0.713235259,
            "b": 0.713235259
          },
          "LayoutGroupSortIndex": 0,
          "Value": 0,
          "Locked": false,
          "Grid": true,
          "Snap": true,
          "IgnoreFoW": false,
          "MeasureMovement": false,
          "DragSelectable": true,
          "Autoraise": true,
          "Sticky": true,
          "Tooltip": true,
          "GridProjection": false,
          "HideWhenFaceDown": true,
          "Hands": true,
          "CardID": 831801,
          "SidewaysCard": false,
          "CustomDeck": {
            "8318": {
              "FaceURL": "https://i.imgur.com/pJw6uZi.png",
              "BackURL": "https://i.imgur.com/Yq7iMBt.jpg",
              "NumWidth": 3,
              "NumHeight": 3,
              "BackIsHidden": true,
              "UniqueBack": false,
              "Type": 0
            }
          },
          "LuaScript": "",
          "LuaScriptState": "",
          "XmlUI": ""
        },
        {
          "GUID": "f81784",
          "Name": "Card",
          "Transform": {
            "posX": 2.68397641,
            "posY": 1.16034031,
            "posZ": 22.7480927,
            "rotX": 0.0004806534,
            "rotY": -0.003413569,
            "rotZ": -0.000716180657,
            "scaleX": 1.25,
            "scaleY": 1.0,
            "scaleZ": 1.25
          },
          "Nickname": "Grasp (N)",
          "Description": "",
          "GMNotes": "",
          "ColorDiffuse": {
            "r": 0.713235259,
            "g": 0.713235259,
            "b": 0.713235259
          },
          "LayoutGroupSortIndex": 0,
          "Value": 0,
          "Locked": false,
          "Grid": true,
          "Snap": true,
          "IgnoreFoW": false,
          "MeasureMovement": false,
          "DragSelectable": true,
          "Autoraise": true,
          "Sticky": true,
          "Tooltip": true,
          "GridProjection": false,
          "HideWhenFaceDown": true,
          "Hands": true,
          "CardID": 831800,
          "SidewaysCard": false,
          "CustomDeck": {
            "8318": {
              "FaceURL": "https://i.imgur.com/pJw6uZi.png",
              "BackURL": "https://i.imgur.com/Yq7iMBt.jpg",
              "NumWidth": 3,
              "NumHeight": 3,
              "BackIsHidden": true,
              "UniqueBack": false,
              "Type": 0
            }
          },
          "LuaScript": "",
          "LuaScriptState": "",
          "XmlUI": ""
        },
        {
          "GUID": "ec4709",
          "Name": "Card",
          "Transform": {
            "posX": 2.69614935,
            "posY": 1.17439437,
            "posZ": 22.9573727,
            "rotX": 0.000449087558,
            "rotY": -0.00341356825,
            "rotZ": -0.0005607316,
            "scaleX": 1.25,
            "scaleY": 1.0,
            "scaleZ": 1.25
          },
          "Nickname": "Grasp (N)",
          "Description": "",
          "GMNotes": "",
          "ColorDiffuse": {
            "r": 0.713235259,
            "g": 0.713235259,
            "b": 0.713235259
          },
          "LayoutGroupSortIndex": 0,
          "Value": 0,
          "Locked": false,
          "Grid": true,
          "Snap": true,
          "IgnoreFoW": false,
          "MeasureMovement": false,
          "DragSelectable": true,
          "Autoraise": true,
          "Sticky": true,
          "Tooltip": true,
          "GridProjection": false,
          "HideWhenFaceDown": true,
          "Hands": true,
          "CardID": 831800,
          "SidewaysCard": false,
          "CustomDeck": {
            "8318": {
              "FaceURL": "https://i.imgur.com/pJw6uZi.png",
              "BackURL": "https://i.imgur.com/Yq7iMBt.jpg",
              "NumWidth": 3,
              "NumHeight": 3,
              "BackIsHidden": true,
              "UniqueBack": false,
              "Type": 0
            }
          },
          "LuaScript": "",
          "LuaScriptState": "",
          "XmlUI": ""
        },
        {
          "GUID": "abc16e",
          "Name": "Card",
          "Transform": {
            "posX": 6.57763529,
            "posY": 1.01496148,
            "posZ": -24.413332,
            "rotX": 358.7619,
            "rotY": 180.0607,
            "rotZ": -0.0002759998,
            "scaleX": 1.25,
            "scaleY": 1.0,
            "scaleZ": 1.25
          },
          "Nickname": "Spellmine (S)",
          "Description": "",
          "GMNotes": "",
          "ColorDiffuse": {
            "r": 0.713235259,
            "g": 0.713235259,
            "b": 0.713235259
          },
          "LayoutGroupSortIndex": 0,
          "Value": 0,
          "Locked": false,
          "Grid": true,
          "Snap": true,
          "IgnoreFoW": false,
          "MeasureMovement": false,
          "DragSelectable": true,
          "Autoraise": true,
          "Sticky": true,
          "Tooltip": true,
          "GridProjection": false,
          "HideWhenFaceDown": true,
          "Hands": true,
          "CardID": 575106,
          "SidewaysCard": false,
          "CustomDeck": {
            "5751": {
              "FaceURL": "https://i.imgur.com/5eX2P1b.jpg",
              "BackURL": "https://i.imgur.com/xSQrDAv.jpg",
              "NumWidth": 4,
              "NumHeight": 2,
              "BackIsHidden": true,
              "UniqueBack": false,
              "Type": 0
            }
          },
          "LuaScript": "",
          "LuaScriptState": "",
          "XmlUI": ""
        },
        {
          "GUID": "002ff2",
          "Name": "Card",
          "Transform": {
            "posX": 6.30890465,
            "posY": 1.0458796,
            "posZ": -23.98037,
            "rotX": 358.76,
            "rotY": 180.060715,
            "rotZ": 359.9924,
            "scaleX": 1.25,
            "scaleY": 1.0,
            "scaleZ": 1.25
          },
          "Nickname": "Spellmine (S)",
          "Description": "",
          "GMNotes": "",
          "ColorDiffuse": {
            "r": 0.713235259,
            "g": 0.713235259,
            "b": 0.713235259
          },
          "LayoutGroupSortIndex": 0,
          "Value": 0,
          "Locked": false,
          "Grid": true,
          "Snap": true,
          "IgnoreFoW": false,
          "MeasureMovement": false,
          "DragSelectable": true,
          "Autoraise": true,
          "Sticky": true,
          "Tooltip": true,
          "GridProjection": false,
          "HideWhenFaceDown": true,
          "Hands": true,
          "CardID": 575106,
          "SidewaysCard": false,
          "CustomDeck": {
            "5751": {
              "FaceURL": "https://i.imgur.com/5eX2P1b.jpg",
              "BackURL": "https://i.imgur.com/xSQrDAv.jpg",
              "NumWidth": 4,
              "NumHeight": 2,
              "BackIsHidden": true,
              "UniqueBack": false,
              "Type": 0
            }
          },
          "LuaScript": "",
          "LuaScriptState": "",
          "XmlUI": ""
        },
        {
          "GUID": "74c96b",
          "Name": "Card",
          "Transform": {
            "posX": 6.331866,
            "posY": 1.08313537,
            "posZ": -24.515564,
            "rotX": 358.7365,
            "rotY": 180.088287,
            "rotZ": -0.00112258119,
            "scaleX": 1.25,
            "scaleY": 1.0,
            "scaleZ": 1.25
          },
          "Nickname": "Blossoming Flare (S)",
          "Description": "",
          "GMNotes": "",
          "ColorDiffuse": {
            "r": 0.713235259,
            "g": 0.713235259,
            "b": 0.713235259
          },
          "LayoutGroupSortIndex": 0,
          "Value": 0,
          "Locked": false,
          "Grid": true,
          "Snap": true,
          "IgnoreFoW": false,
          "MeasureMovement": false,
          "DragSelectable": true,
          "Autoraise": true,
          "Sticky": true,
          "Tooltip": true,
          "GridProjection": false,
          "HideWhenFaceDown": true,
          "Hands": true,
          "CardID": 575105,
          "SidewaysCard": false,
          "CustomDeck": {
            "5751": {
              "FaceURL": "https://i.imgur.com/5eX2P1b.jpg",
              "BackURL": "https://i.imgur.com/xSQrDAv.jpg",
              "NumWidth": 4,
              "NumHeight": 2,
              "BackIsHidden": true,
              "UniqueBack": false,
              "Type": 0
            }
          },
          "LuaScript": "",
          "LuaScriptState": "",
          "XmlUI": ""
        },
        {
          "GUID": "e55da9",
          "Name": "Card",
          "Transform": {
            "posX": 6.44817448,
            "posY": 1.10126889,
            "posZ": -24.4258747,
            "rotX": 358.737579,
            "rotY": 180.025681,
            "rotZ": -0.00444930373,
            "scaleX": 1.25,
            "scaleY": 1.0,
            "scaleZ": 1.25
          },
          "Nickname": "Blossoming Flare (S)",
          "Description": "",
          "GMNotes": "",
          "ColorDiffuse": {
            "r": 0.713235259,
            "g": 0.713235259,
            "b": 0.713235259
          },
          "LayoutGroupSortIndex": 0,
          "Value": 0,
          "Locked": false,
          "Grid": true,
          "Snap": true,
          "IgnoreFoW": false,
          "MeasureMovement": false,
          "DragSelectable": true,
          "Autoraise": true,
          "Sticky": true,
          "Tooltip": true,
          "GridProjection": false,
          "HideWhenFaceDown": true,
          "Hands": true,
          "CardID": 575105,
          "SidewaysCard": false,
          "CustomDeck": {
            "5751": {
              "FaceURL": "https://i.imgur.com/5eX2P1b.jpg",
              "BackURL": "https://i.imgur.com/xSQrDAv.jpg",
              "NumWidth": 4,
              "NumHeight": 2,
              "BackIsHidden": true,
              "UniqueBack": false,
              "Type": 0
            }
          },
          "LuaScript": "",
          "LuaScriptState": "",
          "XmlUI": ""
        },
        {
          "GUID": "f3ce8b",
          "Name": "Card",
          "Transform": {
            "posX": 7.702454,
            "posY": 1.11177146,
            "posZ": -24.3995686,
            "rotX": 358.721069,
            "rotY": 180.011871,
            "rotZ": -0.0016218964,
            "scaleX": 1.25,
            "scaleY": 1.0,
            "scaleZ": 1.25
          },
          "Nickname": "Blasting Orb (S)",
          "Description": "",
          "GMNotes": "",
          "ColorDiffuse": {
            "r": 0.713235259,
            "g": 0.713235259,
            "b": 0.713235259
          },
          "LayoutGroupSortIndex": 0,
          "Value": 0,
          "Locked": false,
          "Grid": true,
          "Snap": true,
          "IgnoreFoW": false,
          "MeasureMovement": false,
          "DragSelectable": true,
          "Autoraise": true,
          "Sticky": true,
          "Tooltip": true,
          "GridProjection": false,
          "HideWhenFaceDown": true,
          "Hands": true,
          "CardID": 575104,
          "SidewaysCard": false,
          "CustomDeck": {
            "5751": {
              "FaceURL": "https://i.imgur.com/5eX2P1b.jpg",
              "BackURL": "https://i.imgur.com/xSQrDAv.jpg",
              "NumWidth": 4,
              "NumHeight": 2,
              "BackIsHidden": true,
              "UniqueBack": false,
              "Type": 0
            }
          },
          "LuaScript": "",
          "LuaScriptState": "",
          "XmlUI": ""
        },
        {
          "GUID": "e0762b",
          "Name": "Card",
          "Transform": {
            "posX": 7.37042,
            "posY": 1.12745821,
            "posZ": -24.7018566,
            "rotX": 358.7215,
            "rotY": 180.011871,
            "rotZ": 0.00128823,
            "scaleX": 1.25,
            "scaleY": 1.0,
            "scaleZ": 1.25
          },
          "Nickname": "Blasting Orb (S)",
          "Description": "",
          "GMNotes": "",
          "ColorDiffuse": {
            "r": 0.713235259,
            "g": 0.713235259,
            "b": 0.713235259
          },
          "LayoutGroupSortIndex": 0,
          "Value": 0,
          "Locked": false,
          "Grid": true,
          "Snap": true,
          "IgnoreFoW": false,
          "MeasureMovement": false,
          "DragSelectable": true,
          "Autoraise": true,
          "Sticky": true,
          "Tooltip": true,
          "GridProjection": false,
          "HideWhenFaceDown": true,
          "Hands": true,
          "CardID": 575104,
          "SidewaysCard": false,
          "CustomDeck": {
            "5751": {
              "FaceURL": "https://i.imgur.com/5eX2P1b.jpg",
              "BackURL": "https://i.imgur.com/xSQrDAv.jpg",
              "NumWidth": 4,
              "NumHeight": 2,
              "BackIsHidden": true,
              "UniqueBack": false,
              "Type": 0
            }
          },
          "LuaScript": "",
          "LuaScriptState": "",
          "XmlUI": ""
        },
        {
          "GUID": "896102",
          "Name": "Card",
          "Transform": {
            "posX": 7.3415575,
            "posY": 1.13912714,
            "posZ": -24.4849663,
            "rotX": 358.766052,
            "rotY": 179.937531,
            "rotZ": 1.50765586,
            "scaleX": 1.25,
            "scaleY": 1.0,
            "scaleZ": 1.25
          },
          "Nickname": "Thunder Crest (S)",
          "Description": "",
          "GMNotes": "",
          "ColorDiffuse": {
            "r": 0.713235259,
            "g": 0.713235259,
            "b": 0.713235259
          },
          "LayoutGroupSortIndex": 0,
          "Value": 0,
          "Locked": false,
          "Grid": true,
          "Snap": true,
          "IgnoreFoW": false,
          "MeasureMovement": false,
          "DragSelectable": true,
          "Autoraise": true,
          "Sticky": true,
          "Tooltip": true,
          "GridProjection": false,
          "HideWhenFaceDown": true,
          "Hands": true,
          "CardID": 575103,
          "SidewaysCard": false,
          "CustomDeck": {
            "5751": {
              "FaceURL": "https://i.imgur.com/5eX2P1b.jpg",
              "BackURL": "https://i.imgur.com/xSQrDAv.jpg",
              "NumWidth": 4,
              "NumHeight": 2,
              "BackIsHidden": true,
              "UniqueBack": false,
              "Type": 0
            }
          },
          "LuaScript": "",
          "LuaScriptState": "",
          "XmlUI": ""
        },
        {
          "GUID": "3e19cc",
          "Name": "Card",
          "Transform": {
            "posX": 6.820103,
            "posY": 1.13785934,
            "posZ": -24.3463879,
            "rotX": 358.753174,
            "rotY": 180.001892,
            "rotZ": -0.00274036149,
            "scaleX": 1.25,
            "scaleY": 1.0,
            "scaleZ": 1.25
          },
          "Nickname": "Thunder Crest (S)",
          "Description": "",
          "GMNotes": "",
          "ColorDiffuse": {
            "r": 0.713235259,
            "g": 0.713235259,
            "b": 0.713235259
          },
          "LayoutGroupSortIndex": 0,
          "Value": 0,
          "Locked": false,
          "Grid": true,
          "Snap": true,
          "IgnoreFoW": false,
          "MeasureMovement": false,
          "DragSelectable": true,
          "Autoraise": true,
          "Sticky": true,
          "Tooltip": true,
          "GridProjection": false,
          "HideWhenFaceDown": true,
          "Hands": true,
          "CardID": 575103,
          "SidewaysCard": false,
          "CustomDeck": {
            "5751": {
              "FaceURL": "https://i.imgur.com/5eX2P1b.jpg",
              "BackURL": "https://i.imgur.com/xSQrDAv.jpg",
              "NumWidth": 4,
              "NumHeight": 2,
              "BackIsHidden": true,
              "UniqueBack": false,
              "Type": 0
            }
          },
          "LuaScript": "",
          "LuaScriptState": "",
          "XmlUI": ""
        },
        {
          "GUID": "1c6235",
          "Name": "Card",
          "Transform": {
            "posX": 6.866261,
            "posY": 1.13847947,
            "posZ": -24.2405682,
            "rotX": 358.76236,
            "rotY": 180.007431,
            "rotZ": 0.000892036,
            "scaleX": 1.25,
            "scaleY": 1.0,
            "scaleZ": 1.25
          },
          "Nickname": "Light Crest (S)",
          "Description": "",
          "GMNotes": "",
          "ColorDiffuse": {
            "r": 0.713235259,
            "g": 0.713235259,
            "b": 0.713235259
          },
          "LayoutGroupSortIndex": 0,
          "Value": 0,
          "Locked": false,
          "Grid": true,
          "Snap": true,
          "IgnoreFoW": false,
          "MeasureMovement": false,
          "DragSelectable": true,
          "Autoraise": true,
          "Sticky": true,
          "Tooltip": true,
          "GridProjection": false,
          "HideWhenFaceDown": true,
          "Hands": true,
          "CardID": 575102,
          "SidewaysCard": false,
          "CustomDeck": {
            "5751": {
              "FaceURL": "https://i.imgur.com/5eX2P1b.jpg",
              "BackURL": "https://i.imgur.com/xSQrDAv.jpg",
              "NumWidth": 4,
              "NumHeight": 2,
              "BackIsHidden": true,
              "UniqueBack": false,
              "Type": 0
            }
          },
          "LuaScript": "",
          "LuaScriptState": "",
          "XmlUI": ""
        },
        {
          "GUID": "7ee17b",
          "Name": "Card",
          "Transform": {
            "posX": 6.95094872,
            "posY": 1.15746415,
            "posZ": -24.32903,
            "rotX": 358.7625,
            "rotY": 180.007431,
            "rotZ": -0.00324527966,
            "scaleX": 1.25,
            "scaleY": 1.0,
            "scaleZ": 1.25
          },
          "Nickname": "Light Crest (S)",
          "Description": "",
          "GMNotes": "",
          "ColorDiffuse": {
            "r": 0.713235259,
            "g": 0.713235259,
            "b": 0.713235259
          },
          "LayoutGroupSortIndex": 0,
          "Value": 0,
          "Locked": false,
          "Grid": true,
          "Snap": true,
          "IgnoreFoW": false,
          "MeasureMovement": false,
          "DragSelectable": true,
          "Autoraise": true,
          "Sticky": true,
          "Tooltip": true,
          "GridProjection": false,
          "HideWhenFaceDown": true,
          "Hands": true,
          "CardID": 575102,
          "SidewaysCard": false,
          "CustomDeck": {
            "5751": {
              "FaceURL": "https://i.imgur.com/5eX2P1b.jpg",
              "BackURL": "https://i.imgur.com/xSQrDAv.jpg",
              "NumWidth": 4,
              "NumHeight": 2,
              "BackIsHidden": true,
              "UniqueBack": false,
              "Type": 0
            }
          },
          "LuaScript": "",
          "LuaScriptState": "",
          "XmlUI": ""
        },
        {
          "GUID": "10529c",
          "Name": "Card",
          "Transform": {
            "posX": 6.908068,
            "posY": 1.15920663,
            "posZ": -24.48793,
            "rotX": 358.7291,
            "rotY": 179.99733,
            "rotZ": -0.00469806837,
            "scaleX": 1.25,
            "scaleY": 1.0,
            "scaleZ": 1.25
          },
          "Nickname": "Radiant Flare (U)",
          "Description": "",
          "GMNotes": "",
          "ColorDiffuse": {
            "r": 0.713235259,
            "g": 0.713235259,
            "b": 0.713235259
          },
          "LayoutGroupSortIndex": 0,
          "Value": 0,
          "Locked": false,
          "Grid": true,
          "Snap": true,
          "IgnoreFoW": false,
          "MeasureMovement": false,
          "DragSelectable": true,
          "Autoraise": true,
          "Sticky": true,
          "Tooltip": true,
          "GridProjection": false,
          "HideWhenFaceDown": true,
          "Hands": true,
          "CardID": 575101,
          "SidewaysCard": false,
          "CustomDeck": {
            "5751": {
              "FaceURL": "https://i.imgur.com/5eX2P1b.jpg",
              "BackURL": "https://i.imgur.com/xSQrDAv.jpg",
              "NumWidth": 4,
              "NumHeight": 2,
              "BackIsHidden": true,
              "UniqueBack": false,
              "Type": 0
            }
          },
          "LuaScript": "",
          "LuaScriptState": "",
          "XmlUI": ""
        },
        {
          "GUID": "fdec7a",
          "Name": "Card",
          "Transform": {
            "posX": 7.27596235,
            "posY": 1.17540932,
            "posZ": -24.2524242,
            "rotX": 358.730652,
            "rotY": 179.995316,
            "rotZ": 0.00547300372,
            "scaleX": 1.25,
            "scaleY": 1.0,
            "scaleZ": 1.25
          },
          "Nickname": "Radiant Flare (U)",
          "Description": "",
          "GMNotes": "",
          "ColorDiffuse": {
            "r": 0.713235259,
            "g": 0.713235259,
            "b": 0.713235259
          },
          "LayoutGroupSortIndex": 0,
          "Value": 0,
          "Locked": false,
          "Grid": true,
          "Snap": true,
          "IgnoreFoW": false,
          "MeasureMovement": false,
          "DragSelectable": true,
          "Autoraise": true,
          "Sticky": true,
          "Tooltip": true,
          "GridProjection": false,
          "HideWhenFaceDown": true,
          "Hands": true,
          "CardID": 575101,
          "SidewaysCard": false,
          "CustomDeck": {
            "5751": {
              "FaceURL": "https://i.imgur.com/5eX2P1b.jpg",
              "BackURL": "https://i.imgur.com/xSQrDAv.jpg",
              "NumWidth": 4,
              "NumHeight": 2,
              "BackIsHidden": true,
              "UniqueBack": false,
              "Type": 0
            }
          },
          "LuaScript": "",
          "LuaScriptState": "",
          "XmlUI": ""
        },
        {
          "GUID": "989bd4",
          "Name": "Card",
          "Transform": {
            "posX": 6.66204548,
            "posY": 1.17969453,
            "posZ": -24.0255051,
            "rotX": 358.758972,
            "rotY": 180.026337,
            "rotZ": -0.000581368746,
            "scaleX": 1.25,
            "scaleY": 1.0,
            "scaleZ": 1.25
          },
          "Nickname": "Starfall (U)",
          "Description": "",
          "GMNotes": "",
          "ColorDiffuse": {
            "r": 0.713235259,
            "g": 0.713235259,
            "b": 0.713235259
          },
          "LayoutGroupSortIndex": 0,
          "Value": 0,
          "Locked": false,
          "Grid": true,
          "Snap": true,
          "IgnoreFoW": false,
          "MeasureMovement": false,
          "DragSelectable": true,
          "Autoraise": true,
          "Sticky": true,
          "Tooltip": true,
          "GridProjection": false,
          "HideWhenFaceDown": true,
          "Hands": true,
          "CardID": 575100,
          "SidewaysCard": false,
          "CustomDeck": {
            "5751": {
              "FaceURL": "https://i.imgur.com/5eX2P1b.jpg",
              "BackURL": "https://i.imgur.com/xSQrDAv.jpg",
              "NumWidth": 4,
              "NumHeight": 2,
              "BackIsHidden": true,
              "UniqueBack": false,
              "Type": 0
            }
          },
          "LuaScript": "",
          "LuaScriptState": "",
          "XmlUI": ""
        },
        {
          "GUID": "ba0b03",
          "Name": "Card",
          "Transform": {
            "posX": 6.82549047,
            "posY": 1.18732917,
            "posZ": -23.88053,
            "rotX": 358.758575,
            "rotY": 180.026337,
            "rotZ": 0.00106896344,
            "scaleX": 1.25,
            "scaleY": 1.0,
            "scaleZ": 1.25
          },
          "Nickname": "Starfall (U)",
          "Description": "",
          "GMNotes": "",
          "ColorDiffuse": {
            "r": 0.713235259,
            "g": 0.713235259,
            "b": 0.713235259
          },
          "LayoutGroupSortIndex": 0,
          "Value": 0,
          "Locked": false,
          "Grid": true,
          "Snap": true,
          "IgnoreFoW": false,
          "MeasureMovement": false,
          "DragSelectable": true,
          "Autoraise": true,
          "Sticky": true,
          "Tooltip": true,
          "GridProjection": false,
          "HideWhenFaceDown": true,
          "Hands": true,
          "CardID": 575100,
          "SidewaysCard": false,
          "CustomDeck": {
            "5751": {
              "FaceURL": "https://i.imgur.com/5eX2P1b.jpg",
              "BackURL": "https://i.imgur.com/xSQrDAv.jpg",
              "NumWidth": 4,
              "NumHeight": 2,
              "BackIsHidden": true,
              "UniqueBack": false,
              "Type": 0
            }
          },
          "LuaScript": "",
          "LuaScriptState": "",
          "XmlUI": ""
        },
        {
          "GUID": "678ab6",
          "Name": "CardCustom",
          "Transform": {
            "posX": 12.9814053,
            "posY": 1.16495419,
            "posZ": -24.1935921,
            "rotX": 0.0004048981,
            "rotY": 180.004059,
            "rotZ": 0.00115595513,
            "scaleX": 1.25,
            "scaleY": 1.0,
            "scaleZ": 1.25
          },
          "Nickname": "Bravery (C)",
          "Description": "",
          "GMNotes": "",
          "ColorDiffuse": {
            "r": 0.713235259,
            "g": 0.713235259,
            "b": 0.713235259
          },
          "LayoutGroupSortIndex": 0,
          "Value": 0,
          "Locked": false,
          "Grid": true,
          "Snap": true,
          "IgnoreFoW": false,
          "MeasureMovement": false,
          "DragSelectable": true,
          "Autoraise": true,
          "Sticky": true,
          "Tooltip": true,
          "GridProjection": false,
          "HideWhenFaceDown": true,
          "Hands": true,
          "CardID": 574500,
          "SidewaysCard": false,
          "CustomDeck": {
            "5745": {
              "FaceURL": "https://i.imgur.com/GGjkL5w.png",
              "BackURL": "https://i.imgur.com/63DdgrF.png",
              "NumWidth": 1,
              "NumHeight": 1,
              "BackIsHidden": true,
              "UniqueBack": false,
              "Type": 0
            }
          },
          "LuaScript": "",
          "LuaScriptState": "",
          "XmlUI": ""
        },
        {
          "GUID": "3536a2",
          "Name": "CardCustom",
          "Transform": {
            "posX": 12.6670818,
            "posY": 1.17436922,
            "posZ": -24.1345444,
            "rotX": 0.000267647469,
            "rotY": 180.0,
            "rotZ": 0.0003911957,
            "scaleX": 1.25768793,
            "scaleY": 1.0,
            "scaleZ": 1.25768793
          },
          "Nickname": "Emperor (C)",
          "Description": "",
          "GMNotes": "",
          "ColorDiffuse": {
            "r": 0.713235259,
            "g": 0.713235259,
            "b": 0.713235259
          },
          "LayoutGroupSortIndex": 0,
          "Value": 0,
          "Locked": false,
          "Grid": true,
          "Snap": true,
          "IgnoreFoW": false,
          "MeasureMovement": false,
          "DragSelectable": true,
          "Autoraise": true,
          "Sticky": true,
          "Tooltip": true,
          "GridProjection": false,
          "HideWhenFaceDown": true,
          "Hands": true,
          "CardID": 575400,
          "SidewaysCard": false,
          "CustomDeck": {
            "5754": {
              "FaceURL": "https://i.imgur.com/7pUeMzo.png",
              "BackURL": "https://i.imgur.com/LKePOkb.png",
              "NumWidth": 1,
              "NumHeight": 1,
              "BackIsHidden": true,
              "UniqueBack": false,
              "Type": 0
            }
          },
          "LuaScript": "",
          "LuaScriptState": "",
          "XmlUI": ""
        }
      ]
    }
  ]
}